bulkhasher.so
bulkhasher/bulkhasher.pyi
bulkhasher/__init__.py
bulkhasher-0.0.5.dist-info/WHEEL
bulkhasher-0.0.5.dist-info/LICENSE
bulkhasher-0.0.5.dist-info/top_level.txt
bulkhasher-0.0.5.dist-info/RECORD
bulkhasher-0.0.5.dist-info/METADATA
bulkhasher.libs/libgomp-1f0f45f5.so.1.0.0
